Ingenieria_Computadores_III/Parte_2/src/gates/puerta_or.vhd
LIBRARY IEEE;
USE IEEE.std_logic_1164.ALL;
ENTITY puerta_or IS
    PORT (
        a, b : IN STD_LOGIC;
        y : OUT STD_LOGIC
    );
END puerta_or;

ARCHITECTURE comportamiento OF puerta_or IS
BEGIN
    y <= a OR b;
END comportamiento;

Ingenieria_Computadores_III/Parte_2/src/gates/puerta_and.vhd
LIBRARY IEEE;
USE IEEE.std_logic_1164.ALL;
ENTITY puerta_and IS
    PORT (
        a, b : IN STD_LOGIC;
        y : OUT STD_LOGIC
    );
END puerta_and;

ARCHITECTURE comportamiento OF puerta_and IS
BEGIN
    y <= a AND b;
END comportamiento;

Ingenieria_Computadores_III/Parte_2/src/gates/puerta_xnor.vhd
LIBRARY IEEE;
USE IEEE.std_logic_1164.ALL;
ENTITY puerta_xnor IS
    PORT (
        a, b : IN STD_LOGIC;
        y : OUT STD_LOGIC
    );
END puerta_xnor;

ARCHITECTURE comportamiento OF puerta_xnor IS
BEGIN
    y <= a XNOR b;
END comportamiento;

Ingenieria_Computadores_III/Parte_1/src/gates/not_gate.vhd
LIBRARY IEEE;
USE IEEE.std_logic_1164.ALL;
ENTITY puerta_not IS
    PORT (
        a : IN STD_LOGIC;
        y : OUT STD_LOGIC
    );
END puerta_not;

ARCHITECTURE comportamiento OF puerta_not IS
BEGIN
    y <= NOT a;
END comportamiento;

Ingenieria_Computadores_III/Parte_2/src/comparador_1bit.vhd
LIBRARY IEEE;
USE IEEE.std_logic_1164.ALL;

ENTITY comparador_1bit IS
    PORT (
        gout, eout : OUT STD_LOGIC;
        gin, ein : IN STD_LOGIC;
        x, y : IN STD_LOGIC
    );
END comparador_1bit;

-- Estructura del comparador de 1 bit
ARCHITECTURE estructura OF comparador_1bit IS
    SIGNAL y_neg : STD_LOGIC;
    SIGNAL x_mayor_y : STD_LOGIC;
    SIGNAL x_igual_y : STD_LOGIC;
    SIGNAL g_temp : STD_LOGIC;
BEGIN
    -- Puerta NOT para negar y
    u1 : ENTITY work.puerta_not PORT MAP (a => y, y => y_neg);

    -- AND para detectar x > y (x=1 y y=0)
    u2 : ENTITY work.puerta_and PORT MAP (a => x, b => y_neg, y => x_mayor_y);

    -- XNOR para detectar igualdad (x == y)
    u3 : ENTITY work.puerta_xnor PORT MAP (a => x, b => y, y => x_igual_y);

    -- AND para propagar la igualdad (ein AND x_igual_y)
    u4 : ENTITY work.puerta_and PORT MAP (a => x_igual_y, b => ein, y => eout);

    -- AND para propagar el mayor anterior (gin AND x_igual_y)
    u5 : ENTITY work.puerta_and PORT MAP (a => x_igual_y, b => gin, y => g_temp);

    -- OR para determinar si x > y (x_mayor_y OR g_temp)
    u6 : ENTITY work.puerta_or PORT MAP (a => x_mayor_y, b => g_temp, y => gout);
END estructura;

Ingenieria_Computadores_III/Parte_2/src/comparador_Nbits.vhd
LIBRARY IEEE;
USE IEEE.std_logic_1164.ALL;
ENTITY comparador_Nbits IS
    GENERIC (N : INTEGER := 4);
    PORT (
        gout, eout : OUT STD_LOGIC;
        gin, ein : IN STD_LOGIC;
        x, y : IN STD_LOGIC_VECTOR (N - 1 DOWNTO 0)
    );
END comparador_Nbits;

ARCHITECTURE estructura OF comparador_Nbits IS
    SIGNAL g_temp, e_temp : STD_LOGIC_VECTOR (N - 1 DOWNTO 0); -- Salidas de cada comparador
    SIGNAL gin_temp, ein_temp : STD_LOGIC_VECTOR (N DOWNTO 0); -- Conexiones en cascada
BEGIN
    gin_temp(0) <= gin; -- gin inicial
    ein_temp(0) <= ein; -- ein inicial

    gen_comparadores : FOR i IN 0 TO N - 1 GENERATE
        comp : ENTITY work.comparador_1bit
            PORT MAP(
                gout => g_temp(i),
                eout => e_temp(i),
                gin => gin_temp(i),
                ein => ein_temp(i),
                x => x(i),
                y => y(i)
            );
        gin_temp(i + 1) <= g_temp(i);
        ein_temp(i + 1) <= e_temp(i);
    END GENERATE;

    gout <= gin_temp(N);
    eout <= ein_temp(N);
END estructura;

Ingenieria_Computadores_III/Parte_2/test/tb_comparador_Nbits.vhd
LIBRARY IEEE;
USE IEEE.std_logic_1164.ALL;
USE IEEE.numeric_std.ALL;

ENTITY tb_comparador_Nbits IS
END tb_comparador_Nbits;

ARCHITECTURE test OF tb_comparador_Nbits IS
    CONSTANT N : INTEGER := 4;
    SIGNAL x, y : STD_LOGIC_VECTOR (N - 1 DOWNTO 0);
    SIGNAL gout, eout : STD_LOGIC;
    SIGNAL gin, ein : STD_LOGIC;

    COMPONENT comparador_Nbits IS
        GENERIC (N : INTEGER := 4);
        PORT (
            gout : OUT STD_LOGIC;
            eout : OUT STD_LOGIC;
            gin : IN STD_LOGIC;
            ein : IN STD_LOGIC;
            x : IN STD_LOGIC_VECTOR (N - 1 DOWNTO 0);
            y : IN STD_LOGIC_VECTOR (N - 1 DOWNTO 0)
        );
    END COMPONENT;
BEGIN
    uut : comparador_Nbits
    GENERIC MAP(N => N)
    PORT MAP(
        gout => gout,
        eout => eout,
        gin => gin,
        ein => ein,
        x => x,
        y => y
    );

    -- Proceso de estimulación
    PROCESS
        VARIABLE error_count : INTEGER := 0;
    BEGIN
        -- Prueba 1: Modo normal (ein=1, gin=0) - Todas combinaciones para N=4
        REPORT "Probando modo normal (ein=1, gin=0) - Todas combinaciones";
        gin <= '0';
        ein <= '1';

        -- Probar todas las combinaciones posibles para N=4
        FOR i IN 0 TO 2 ** N - 1 LOOP
            FOR j IN 0 TO 2 ** N - 1 LOOP
                x <= STD_LOGIC_VECTOR(to_unsigned(i, N));
                y <= STD_LOGIC_VECTOR(to_unsigned(j, N));
                WAIT FOR 10 ns;

                -- Verificación
                IF (i > j AND gout /= '1') OR (i <= j AND gout = '1') THEN
                    error_count := error_count + 1;
                END IF;

                IF (i = j AND eout /= '1') OR (i /= j AND eout = '1') THEN
                    error_count := error_count + 1;
                END IF;
            END LOOP;
        END LOOP;

        -- Prueba 2: Casos específicos críticos de la tabla de verdad
        REPORT "Probando casos especificos criticos de la tabla de verdad";

        -- Caso 2.1: x=0, y=0, ein=1 (debería activar eout)
        REPORT "  Probando x=0,y=0,ein=1 (deberia activar eout)";
        gin <= '0';
        ein <= '1';
        x <= "0000"; -- 0
        y <= "0000"; -- 0
        WAIT FOR 10 ns;
        IF eout /= '1' THEN
            REPORT "Error: x=0,y=0,ein=1 pero eout no es 1" SEVERITY error;
            error_count := error_count + 1;
        END IF;

        -- Caso 2.2: x=0, y=0, gin=1 (debería activar gout)
        REPORT "  Probando x=0,y=0,gin=1 (deberia activar gout)";
        gin <= '1';
        ein <= '0';
        x <= "0000"; -- 0
        y <= "0000"; -- 0
        WAIT FOR 10 ns;
        IF gout /= '1' THEN
            REPORT "Error: x=0,y=0,gin=1 pero gout no es 1" SEVERITY error;
            error_count := error_count + 1;
        END IF;

        -- Caso 2.3: x=1, y=0, ein=1 (debería activar gout)
        REPORT "  Probando x=1,y=0,ein=1 (deberia activar gout)";
        gin <= '0';
        ein <= '1';
        x <= "0001"; -- 1
        y <= "0000"; -- 0
        WAIT FOR 10 ns;
        IF gout /= '1' THEN
            REPORT "Error: x=1,y=0,ein=1 pero gout no es 1" SEVERITY error;
            error_count := error_count + 1;
        END IF;

        -- Caso 2.4: x=1, y=0, gin=1, ein=0 (debería activar gout)
        REPORT "  Probando x=1,y=0,gin=1,ein=0 (deberia activar gout)";
        gin <= '1';
        ein <= '0';
        x <= "0001"; -- 1
        y <= "0000"; -- 0
        WAIT FOR 10 ns;
        IF gout /= '1' THEN
            REPORT "Error: x=1,y=0,gin=1,ein=0 pero gout no es 1" SEVERITY error;
            error_count := error_count + 1;
        END IF;
        IF eout /= '0' THEN
            REPORT "Error: x=1,y=0,gin=1,ein=0 pero eout no es 0" SEVERITY error;
            error_count := error_count + 1;
        END IF;

        -- Caso 2.5: x=1, y=1, gin=0, ein=1 (debería activar eout)
        REPORT "  Probando x=1,y=1,gin=0,ein=1 (deberia activar eout)";
        gin <= '0';
        ein <= '1';
        x <= "0001"; -- 1
        y <= "0001"; -- 1
        WAIT FOR 10 ns;
        IF eout /= '1' THEN
            REPORT "Error: x=1,y=1,gin=0,ein=1 pero eout no es 1" SEVERITY error;
            error_count := error_count + 1;
        END IF;

        -- Caso 2.6: x=1, y=1, gin=1, ein=0 (debería activar gout)
        REPORT "  Probando x=1,y=1,gin=1,ein=0 (deberia activar gout)";
        gin <= '1';
        ein <= '0';
        x <= "0001"; -- 1
        y <= "0001"; -- 1
        WAIT FOR 10 ns;
        IF gout /= '1' THEN
            REPORT "Error: x=1,y=1,gin=1,ein=0 pero gout no es 1" SEVERITY error;
            error_count := error_count + 1;
        END IF;

        -- Prueba 3: Caso especial del testbench original
        REPORT "Probando caso especial del testbench original";

        -- Caso 3.1: gin=1, ein=1 con x=y (comportamiento especial)
        REPORT "  Probando gin=1,ein=1 con x=y (comportamiento especial)";
        gin <= '1';
        ein <= '1';
        x <= "0101"; -- 5
        y <= "0101"; -- 5
        WAIT FOR 10 ns;
        IF gout /= '1' THEN
            REPORT "Error: gin=1,ein=1 con x=y pero gout=0" SEVERITY error;
            error_count := error_count + 1;
        END IF;
        IF eout /= '1' THEN
            REPORT "Error: gin=1,ein=1 con x=y pero eout=0" SEVERITY error;
            error_count := error_count + 1;
        END IF;

        -- Resumen final
        IF error_count = 0 THEN
            REPORT "¡Todos los tests pasaron correctamente!" SEVERITY note;
        ELSE
            REPORT "Prueba fallida con " & INTEGER'image(error_count) & " errores" SEVERITY error;
        END IF;

        WAIT;
    END PROCESS;
END test;

Ingenieria_Computadores_III/Parte_2/diagrama_parte_2.vcd
$date
  Wed Apr 09 19:53:25 2025
$end
$version
  GHDL v0
$end
$timescale
  1 fs
$end
$scope module standard $end
$upscope $end
$scope module std_logic_1164 $end
$upscope $end
$scope module numeric_std $end
$upscope $end
$scope module tb_comparador_nbits $end
$var reg 4 ! x[3:0] $end
$var reg 4 " y[3:0] $end
$var reg 1 # gout $end
$var reg 1 $ eout $end
$var reg 1 % gin $end
$var reg 1 & ein $end
$scope module uut $end
$var reg 1 ' gout $end
$var reg 1 ( eout $end
$var reg 1 ) gin $end
$var reg 1 * ein $end
$var reg 4 + x[3:0] $end
$var reg 4 , y[3:0] $end
$var reg 4 - g_temp[3:0] $end
$var reg 4 . e_temp[3:0] $end
$var reg 5 / gin_temp[4:0] $end
$var reg 5 0 ein_temp[4:0] $end
$scope module gen_comparadores(0) $end
$scope module comp $end
$var reg 1 1 gout $end
$var reg 1 2 eout $end
$var reg 1 3 gin $end
$var reg 1 4 ein $end
$var reg 1 5 x $end
$var reg 1 6 y $end
$var reg 1 7 y_neg $end
$var reg 1 8 x_mayor_y $end
$var reg 1 9 x_igual_y $end
$var reg 1 : g_temp $end
$scope module u1 $end
$var reg 1 ; a $end
$var reg 1 < y $end
$upscope $end
$scope module u2 $end
$var reg 1 = a $end
$var reg 1 > b $end
$var reg 1 ? y $end
$upscope $end
$scope module u3 $end
$var reg 1 @ a $end
$var reg 1 A b $end
$var reg 1 B y $end
$upscope $end
$scope module u4 $end
$var reg 1 C a $end
$var reg 1 D b $end
$var reg 1 E y $end
$upscope $end
$scope module u5 $end
$var reg 1 F a $end
$var reg 1 G b $end
$var reg 1 H y $end
$upscope $end
$scope module u6 $end
$var reg 1 I a $end
$var reg 1 J b $end
$var reg 1 K y $end
$upscope $end
$upscope $end
$upscope $end
$scope module gen_comparadores(1) $end
$scope module comp $end
$var reg 1 L gout $end
$var reg 1 M eout $end
$var reg 1 N gin $end
$var reg 1 O ein $end
$var reg 1 P x $end
$var reg 1 Q y $end
$var reg 1 R y_neg $end
$var reg 1 S x_mayor_y $end
$var reg 1 T x_igual_y $end
$var reg 1 U g_temp $end
$scope module u1 $end
$var reg 1 V a $end
$var reg 1 W y $end
$upscope $end
$scope module u2 $end
$var reg 1 X a $end
$var reg 1 Y b $end
$var reg 1 Z y $end
$upscope $end
$scope module u3 $end
$var reg 1 [ a $end
$var reg 1 \ b $end
$var reg 1 ] y $end
$upscope $end
$scope module u4 $end
$var reg 1 ^ a $end
$var reg 1 _ b $end
$var reg 1 ` y $end
$upscope $end
$scope module u5 $end
$var reg 1 a a $end
$var reg 1 b b $end
$var reg 1 c y $end
$upscope $end
$scope module u6 $end
$var reg 1 d a $end
$var reg 1 e b $end
$var reg 1 f y $end
$upscope $end
$upscope $end
$upscope $end
$scope module gen_comparadores(2) $end
$scope module comp $end
$var reg 1 g gout $end
$var reg 1 h eout $end
$var reg 1 i gin $end
$var reg 1 j ein $end
$var reg 1 k x $end
$var reg 1 l y $end
$var reg 1 m y_neg $end
$var reg 1 n x_mayor_y $end
$var reg 1 o x_igual_y $end
$var reg 1 p g_temp $end
$scope module u1 $end
$var reg 1 q a $end
$var reg 1 r y $end
$upscope $end
$scope module u2 $end
$var reg 1 s a $end
$var reg 1 t b $end
$var reg 1 u y $end
$upscope $end
$scope module u3 $end
$var reg 1 v a $end
$var reg 1 w b $end
$var reg 1 x y $end
$upscope $end
$scope module u4 $end
$var reg 1 y a $end
$var reg 1 z b $end
$var reg 1 { y $end
$upscope $end
$scope module u5 $end
$var reg 1 | a $end
$var reg 1 } b $end
$var reg 1 !" y $end
$upscope $end
$scope module u6 $end
$var reg 1 "" a $end
$var reg 1 #" b $end
$var reg 1 $" y $end
$upscope $end
$upscope $end
$upscope $end
$scope module gen_comparadores(3) $end
$scope module comp $end
$var reg 1 %" gout $end
$var reg 1 &" eout $end
$var reg 1 '" gin $end
$var reg 1 (" ein $end
$var reg 1 )" x $end
$var reg 1 *" y $end
$var reg 1 +" y_neg $end
$var reg 1 ," x_mayor_y $end
$var reg 1 -" x_igual_y $end
$var reg 1 ." g_temp $end
$scope module u1 $end
$var reg 1 /" a $end
$var reg 1 0" y $end
$upscope $end
$scope module u2 $end
$var reg 1 1" a $end
$var reg 1 2" b $end
$var reg 1 3" y $end
$upscope $end
$scope module u3 $end
$var reg 1 4" a $end
$var reg 1 5" b $end
$var reg 1 6" y $end
$upscope $end
$scope module u4 $end
$var reg 1 7" a $end
$var reg 1 8" b $end
$var reg 1 9" y $end
$upscope $end
$scope module u5 $end
$var reg 1 :" a $end
$var reg 1 ;" b $end
$var reg 1 <" y $end
$upscope $end
$scope module u6 $end
$var reg 1 =" a $end
$var reg 1 >" b $end
$var reg 1 ?" y $end
$upscope $end
$upscope $end
$upscope $end
$upscope $end
$upscope $end
$enddefinitions $end
#0
b0000 !
b0000 "
0#
1$
0%
1&
0'
1(
0)
1*
b0000 +
b0000 ,
b0000 -
b1111 .
b00000 /
b11111 0
01
12
03
14
05
06
17
08
19
0:
0;
1<
0=
1>
0?
0@
0A
1B
1C
1D
1E
1F
0G
0H
0I
0J
0K
0L
1M
0N
1O
0P
0Q
1R
0S
1T
0U
0V
1W
0X
1Y
0Z
0[
0\
1]
1^
1_
1`
1a
0b
0c
0d
0e
0f
0g
1h
0i
1j
0k
0l
1m
0n
1o
0p
0q
1r
0s
1t
0u
0v
0w
1x
1y
1z
1{
1|
0}
0!"
0""
0#"
0$"
0%"
1&"
0'"
1("
0)"
0*"
1+"
0,"
1-"
0."
0/"
10"
01"
12"
03"
04"
05"
16"
17"
18"
19"
1:"
0;"
0<"
0="
0>"
0?"
#10000000
b0001 "
0$
0(
b0001 ,
b0000 .
b00001 0
02
16
07
09
1;
0<
0>
1A
0B
0C
0E
0F
0M
0O
0_
0`
0h
0j
0z
0{
0&"
0("
08"
09"
#20000000
b0010 "
b0010 ,
b0001 .
b00011 0
12
06
17
19
0;
1<
1>
0A
1B
1C
1E
1F
1O
1Q
0R
0T
1V
0W
0Y
1\
0]
0^
1_
0a
#30000000
b0011 "
b0011 ,
b0000 .
b00001 0
02
16
07
09
1;
0<
0>
1A
0B
0C
0E
0F
0O
0_
#40000000
b0100 "
b0100 ,
b0011 .
b00111 0
12
06
17
19
0;
1<
1>
0A
1B
1C
1E
1F
1M
1O
0Q
1R
1T
0V
1W
1Y
0\
1]
1^
1_
1`
1a
1j
1l
0m
0o
1q
0r
0t
1w
0x
0y
1z
0|
#50000000
b0101 "
b0101 ,
b0000 .
b00001 0
02
16
07
09
1;
0<
0>
1A
0B
0C
0E
0F
0M
0O
0_
0`
0j
0z
#60000000
b0110 "
b0110 ,
b0001 .
b00011 0
12
06
17
19
0;
1<
1>
0A
1B
1C
1E
1F
1O
1Q
0R
0T
1V
0W
0Y
1\
0]
0^
1_
0a
#70000000
b0111 "
b0111 ,
b0000 .
b00001 0
02
16
07
09
1;
0<
0>
1A
0B
0C
0E
0F
0O
0_
#80000000
b1000 "
b1000 ,
b0111 .
b01111 0
12
06
17
19
0;
1<
1>
0A
1B
1C
1E
1F
1M
1O
0Q
1R
1T
0V
1W
1Y
0\
1]
1^
1_
1`
1a
1h
1j
0l
1m
1o
0q
1r
1t
0w
1x
1y
1z
1{
1|
1("
1*"
0+"
0-"
1/"
00"
02"
15"
06"
07"
18"
0:"
#90000000
b1001 "
b1001 ,
b0000 .
b00001 0
02
16
07
09
1;
0<
0>
1A
0B
0C
0E
0F
0M
0O
0_
0`
0h
0j
0z
0{
0("
08"
#100000000
b1010 "
b1010 ,
b0001 .
b00011 0
12
06
17
19
0;
1<
1>
0A
1B
1C
1E
1F
1O
1Q
0R
0T
1V
0W
0Y
1\
0]
0^
1_
0a
#110000000
b1011 "
b1011 ,
b0000 .
b00001 0
02
16
07
09
1;
0<
0>
1A
0B
0C
0E
0F
0O
0_
#120000000
b1100 "
b1100 ,
b0011 .
b00111 0
12
06
17
19
0;
1<
1>
0A
1B
1C
1E
1F
1M
1O
0Q
1R
1T
0V
1W
1Y
0\
1]
1^
1_
1`
1a
1j
1l
0m
0o
1q
0r
0t
1w
0x
0y
1z
0|
#130000000
b1101 "
b1101 ,
b0000 .
b00001 0
02
16
07
09
1;
0<
0>
1A
0B
0C
0E
0F
0M
0O
0_
0`
0j
0z
#140000000
b1110 "
b1110 ,
b0001 .
b00011 0
12
06
17
19
0;
1<
1>
0A
1B
1C
1E
1F
1O
1Q
0R
0T
1V
0W
0Y
1\
0]
0^
1_
0a
#150000000
b1111 "
b1111 ,
b0000 .
b00001 0
02
16
07
09
1;
0<
0>
1A
0B
0C
0E
0F
0O
0_
#160000000
b0001 !
b0000 "
1#
1'
b0001 +
b0000 ,
b1111 -
b11110 /
11
15
06
17
18
0;
1<
1=
1>
1?
1@
0A
1I
1K
1L
1N
0Q
1R
1T
1U
0V
1W
1Y
0\
1]
1^
1a
1b
1c
1e
1f
1g
1i
0l
1m
1o
1p
0q
1r
1t
0w
1x
1y
1|
1}
1!"
1#"
1$"
1%"
1'"
0*"
1+"
1-"
1."
0/"
10"
12"
05"
16"
17"
1:"
1;"
1<"
1>"
1?"
#170000000
b0001 "
0#
1$
0'
1(
b0001 ,
b0000 -
b1111 .
b00000 /
b11111 0
01
12
16
07
08
19
1;
0<
0>
0?
1A
1B
1C
1E
1F
0I
0K
0L
1M
0N
1O
0U
1_
1`
0b
0c
0e
0f
0g
1h
0i
1j
0p
1z
1{
0}
0!"
0#"
0$"
0%"
1&"
0'"
1("
0."
18"
19"
0;"
0<"
0>"
0?"
#180000000
b0010 "
0$
0(
b0010 ,
b0001 -
b0000 .
b00010 /
b00001 0
11
02
06
17
18
09
0;
1<
1>
1?
0A
0B
0C
0E
0F
1I
1K
0M
1N
0O
1Q
0R
0T
1V
0W
0Y
1\
0]
0^
0_
0`
0a
1b
0h
0j
0z
0{
0&"
0("
08"
09"
#190000000
b0011 "
b0011 ,
b0000 -
b0001 .
b00000 /
b00011 0
01
12
16
07
08
19
1;
0<
0>
0?
1A
1B
1C
1E
1F
0I
0K
0N
1O
1_
0b
#200000000
b0100 "
b0100 ,
b0011 -
b0000 .
b00110 /
b00001 0
11
02
06
17
18
09
0;
1<
1>
1?
0A
0B
0C
0E
0F
1I
1K
1L
0M
1N
0O
0Q
1R
1T
1U
0V
1W
1Y
0\
1]
1^
0_
0`
1a
1b
1c
1e
1f
1i
0j
1l
0m
0o
1q
0r
0t
1w
0x
0y
0z
0|
1}
#210000000
b0101 "
b0101 ,
b0000 -
b0011 .
b00000 /
b00111 0
01
12
16
07
08
19
1;
0<
0>
0?
1A
1B
1C
1E
1F
0I
0K
0L
1M
0N
1O
0U
1_
1`
0b
0c
0e
0f
0i
1j
1z
0}
#220000000
b0110 "
b0110 ,
b0001 -
b0000 .
b00010 /
b00001 0
11
02
06
17
18
09
0;
1<
1>
1?
0A
0B
0C
0E
0F
1I
1K
0M
1N
0O
1Q
0R
0T
1V
0W
0Y
1\
0]
0^
0_
0`
0a
1b
0j
0z
#230000000
b0111 "
b0111 ,
b0000 -
b0001 .
b00000 /
b00011 0
01
12
16
07
08
19
1;
0<
0>
0?
1A
1B
1C
1E
1F
0I
0K
0N
1O
1_
0b
#240000000
b1000 "
b1000 ,
b0111 -
b0000 .
b01110 /
b00001 0
11
02
06
17
18
09
0;
1<
1>
1?
0A
0B
0C
0E
0F
1I
1K
1L
0M
1N
0O
0Q
1R
1T
1U
0V
1W
1Y
0\
1]
1^
0_
0`
1a
1b
1c
1e
1f
1g
0h
1i
0j
0l
1m
1o
1p
0q
1r
1t
0w
1x
1y
0z
0{
1|
1}
1!"
1#"
1$"
1'"
0("
1*"
0+"
0-"
1/"
00"
02"
15"
06"
07"
08"
0:"
1;"
#250000000
b1001 "
b1001 ,
b0000 -
b0111 .
b00000 /
b01111 0
01
12
16
07
08
19
1;
0<
0>
0?
1A
1B
1C
1E
1F
0I
0K
0L
1M
0N
1O
0U
1_
1`
0b
0c
0e
0f
0g
1h
0i
1j
0p
1z
1{
0}
0!"
0#"
0$"
0'"
1("
18"
0;"
#260000000
b1010 "
b1010 ,
b0001 -
b0000 .
b00010 /
b00001 0
11
02
06
17
18
09
0;
1<
1>
1?
0A
0B
0C
0E
0F
1I
1K
0M
1N
0O
1Q
0R
0T
1V
0W
0Y
1\
0]
0^
0_
0`
0a
1b
0h
0j
0z
0{
0("
08"
#270000000
b1011 "
b1011 ,
b0000 -
b0001 .
b00000 /
b00011 0
01
12
16
07
08
19
1;
0<
0>
0?
1A
1B
1C
1E
1F
0I
0K
0N
1O
1_
0b
#280000000
b1100 "
b1100 ,
b0011 -
b0000 .
b00110 /
b00001 0
11
02
06
17
18
09
0;
1<
1>
1?
0A
0B
0C
0E
0F
1I
1K
1L
0M
1N
0O
0Q
1R
1T
1U
0V
1W
1Y
0\
1]
1^
0_
0`
1a
1b
1c
1e
1f
1i
0j
1l
0m
0o
1q
0r
0t
1w
0x
0y
0z
0|
1}
#290000000
b1101 "
b1101 ,
b0000 -
b0011 .
b00000 /
b00111 0
01
12
16
07
08
19
1;
0<
0>
0?
1A
1B
1C
1E
1F
0I
0K
0L
1M
0N
1O
0U
1_
1`
0b
0c
0e
0f
0i
1j
1z
0}
#300000000
b1110 "
b1110 ,
b0001 -
b0000 .
b00010 /
b00001 0
11
02
06
17
18
09
0;
1<
1>
1?
0A
0B
0C
0E
0F
1I
1K
0M
1N
0O
1Q
0R
0T
1V
0W
0Y
1\
0]
0^
0_
0`
0a
1b
0j
0z
#310000000
b1111 "
b1111 ,
b0000 -
b0001 .
b00000 /
b00011 0
01
12
16
07
08
19
1;
0<
0>
0?
1A
1B
1C
1E
1F
0I
0K
0N
1O
1_
0b
#320000000
b0010 !
b0000 "
1#
1'
b0010 +
b0000 ,
b1110 -
b11100 /
05
06
17
0;
1<
0=
1>
0@
0A
1L
1P
0Q
1R
1S
0V
1W
1X
1Y
1Z
1[
0\
1d
1f
1g
1i
0l
1m
1o
1p
0q
1r
1t
0w
1x
1y
1|
1}
1!"
1#"
1$"
1%"
1'"
0*"
1+"
1-"
1."
0/"
10"
12"
05"
16"
17"
1:"
1;"
1<"
1>"
1?"
#330000000
b0001 "
b0001 ,
b0000 .
b00001 0
02
16
07
09
1;
0<
0>
1A
0B
0C
0E
0F
0O
0_
#340000000
b0010 "
0#
1$
0'
1(
b0010 ,
b0000 -
b1111 .
b00000 /
b11111 0
12
06
17
19
0;
1<
1>
0A
1B
1C
1E
1F
0L
1M
1O
1Q
0R
0S
1T
1V
0W
0Y
0Z
1\
1]
1^
1_
1`
1a
0d
0f
0g
1h
0i
1j
0p
1z
1{
0}
0!"
0#"
0$"
0%"
1&"
0'"
1("
0."
18"
19"
0;"
0<"
0>"
0?"
#350000000
b0011 "
0$
0(
b0011 ,
b0000 .
b00001 0
02
16
07
09
1;
0<
0>
1A
0B
0C
0E
0F
0M
0O
0_
0`
0h
0j
0z
0{
0&"
0("
08"
09"
#360000000
b0100 "
b0100 ,
b0010 -
b0001 .
b00100 /
b00011 0
12
06
17
19
0;
1<
1>
0A
1B
1C
1E
1F
1L
1O
0Q
1R
1S
0T
0V
1W
1Y
1Z
0\
0]
0^
1_
0a
1d
1f
1i
1l
0m
0o
1q
0r
0t
1w
0x
0y
0|
1}
#370000000
b0101 "
b0101 ,
b0000 .
b00001 0
02
16
07
09
1;
0<
0>
1A
0B
0C
0E
0F
0O
0_
#380000000
b0110 "
b0110 ,
b0000 -
b0011 .
b00000 /
b00111 0
12
06
17
19
0;
1<
1>
0A
1B
1C
1E
1F
0L
1M
1O
1Q
0R
0S
1T
1V
0W
0Y
0Z
1\
1]
1^
1_
1`
1a
0d
0f
0i
1j
1z
0}
#390000000
b0111 "
b0111 ,
b0000 .
b00001 0
02
16
07
09
1;
0<
0>
1A
0B
0C
0E
0F
0M
0O
0_
0`
0j
0z
#400000000
b1000 "
b1000 ,
b0110 -
b0001 .
b01100 /
b00011 0
12
06
17
19
0;
1<
1>
0A
1B
1C
1E
1F
1L
1O
0Q
1R
1S
0T
0V
1W
1Y
1Z
0\
0]
0^
1_
0a
1d
1f
1g
1i
0l
1m
1o
1p
0q
1r
1t
0w
1x
1y
1|
1}
1!"
1#"
1$"
1'"
1*"
0+"
0-"
1/"
00"
02"
15"
06"
07"
0:"
1;"
#410000000
b1001 "
b1001 ,
b0000 .
b00001 0
02
16
07
09
1;
0<
0>
1A
0B
0C
0E
0F
0O
0_
#420000000
b1010 "
b1010 ,
b0000 -
b0111 .
b00000 /
b01111 0
12
06
17
19
0;
1<
1>
0A
1B
1C
1E
1F
0L
1M
1O
1Q
0R
0S
1T
1V
0W
0Y
0Z
1\
1]
1^
1_
1`
1a
0d
0f
0g
1h
0i
1j
0p
1z
1{
0}
0!"
0#"
0$"
0'"
1("
18"
0;"
#430000000
b1011 "
b1011 ,
b0000 .
b00001 0
02
16
07
09
1;
0<
0>
1A
0B
0C
0E
0F
0M
0O
0_
0`
0h
0j
0z
0{
0("
08"
#440000000
b1100 "
b1100 ,
b0010 -
b0001 .
b00100 /
b00011 0
12
06
17
19
0;
1<
1>
0A
1B
1C
1E
1F
1L
1O
0Q
1R
1S
0T
0V
1W
1Y
1Z
0\
0]
0^
1_
0a
1d
1f
1i
1l
0m
0o
1q
0r
0t
1w
0x
0y
0|
1}
#450000000
b1101 "
b1101 ,
b0000 .
b00001 0
02
16
07
09
1;
0<
0>
1A
0B
0C
0E
0F
0O
0_
#460000000
b1110 "
b1110 ,
b0000 -
b0011 .
b00000 /
b00111 0
12
06
17
19
0;
1<
1>
0A
1B
1C
1E
1F
0L
1M
1O
1Q
0R
0S
1T
1V
0W
0Y
0Z
1\
1]
1^
1_
1`
1a
0d
0f
0i
1j
1z
0}
#470000000
b1111 "
b1111 ,
b0000 .
b00001 0
02
16
07
09
1;
0<
0>
1A
0B
0C
0E
0F
0M
0O
0_
0`
0j
0z
#480000000
b0011 !
b0000 "
1#
1'
b0011 +
b0000 ,
b1111 -
b11110 /
11
15
06
17
18
0;
1<
1=
1>
1?
1@
0A
1I
1K
1L
1N
0Q
1R
1S
0T
0V
1W
1Y
1Z
0\
0]
0^
0a
1b
1d
1f
1g
1i
0l
1m
1o
1p
0q
1r
1t
0w
1x
1y
1|
1}
1!"
1#"
1$"
1%"
1'"
0*"
1+"
1-"
1."
0/"
10"
12"
05"
16"
17"
1:"
1;"
1<"
1>"
1?"
#490000000
b0001 "
b0001 ,
b1110 -
b0001 .
b11100 /
b00011 0
01
12
16
07
08
19
1;
0<
0>
0?
1A
1B
1C
1E
1F
0I
0K
0N
1O
1_
0b
#500000000
b0010 "
1#
0$
1'
0(
b0010 ,
b1111 -
b0000 .
b11110 /
b00001 0
11
02
06
17
18
09
0;
1<
1>
1?
0A
0B
0C
0E
0F
1I
1K
1L
0M
1N
0O
1Q
0R
0S
1T
1U
1V
0W
0Y
0Z
1\
1]
1^
0_
0`
1a
1b
1c
0d
1e
1f
1g
0h
1i
0j
1p
0z
0{
1}
1!"
1#"
1$"
1%"
0&"
1'"
0("
1."
08"
09"
1;"
1<"
1>"
1?"
#510000000
b0011 "
0#
1$
0'
1(
b0011 ,
b0000 -
b1111 .
b00000 /
b11111 0
01
12
16
07
08
19
1;
0<
0>
0?
1A
1B
1C
1E
1F
0I
0K
0L
1M
0N
1O
0U
1_
1`
0b
0c
0e
0f
0g
1h
0i
1j
0p
1z
1{
0}
0!"
0#"
0$"
0%"
1&"
0'"
1("
0."
18"
19"
0;"
0<"
0>"
0?"
#520000000
b0100 "
0$
0(
b0100 ,
b0011 -
b0000 .
b00110 /
b00001 0
11
02
06
17
18
09
0;
1<
1>
1?
0A
0B
0C
0E
0F
1I
1K
1L
0M
1N
0O
0Q
1R
1S
0T
0V
1W
1Y
1Z
0\
0]
0^
0_
0`
0a
1b
1d
1f
0h
1i
0j
1l
0m
0o
1q
0r
0t
1w
0x
0y
0z
0{
0|
1}
0&"
0("
08"
09"
#530000000
b0101 "
b0101 ,
b0010 -
b0001 .
b00100 /
b00011 0
01
12
16
07
08
19
1;
0<
0>
0?
1A
1B
1C
1E
1F
0I
0K
0N
1O
1_
0b
