IC_III/Parte_2/Parte_2.vhdl
-- a)
library IEEE;
use IEEE.Std_logic_1164.all;
use IEEE.Numeric_Std.all;
entity comparador_1bit is
    port (  gout: out std_logic;
            eout: out std_logic;
            gin: in std_logic;
            ein: in std_logic;
            x: in std_logic;
            y: in std_logic
    );
end comparador_1bit;

library IEEE;
use IEEE.Std_logic_1164.all;
use IEEE.Numeric_Std.all;
entity comparador_Nbits is
    generic ( N: integer := 4);
    port(   gout: out std_logic;
            eout: out std_logic;
            gin: in std_logic;
            ein: in std_logic;
            x: in std_logic (N-1 downto 0);
            y: in std_logic (N-1 downto 0)
    );
end comparador_Nbits;

-- b)

library IEEE;
use IEEE.Std_logic_1164.all;
use IEEE.Numeric_Std.all;
entity and_gate is
    port (  a, b: in std_logic;
            y: out std_logic
    );
end and_gate;

architecture behavior of and_gate is
begin
    y <= a and b;
end behavior;

library IEEE;
use IEEE.Std_logic_1164.all;
use IEEE.Numeric_Std.all;
entity or_gate is
    port (  a, b: in std_logic;
            y: out std_logic
    );
end or_gate;

architecture behavior of or_gate is
begin
    y <= a or b;
end behavior;

library IEEE;
use IEEE.Std_logic_1164.all;
use IEEE.Numeric_Std.all;
entity xnor_gate is
    port (  a, b: in std_logic;
            y: out std_logic
    );
end xnor_gate;

architecture behavior of xnor_gate is
begin
    y <= a xnor b;
end behavior;

library IEEE;
use IEEE.Std_logic_1164.all;
use IEEE.Numeric_Std.all;
entity not_gate is
    port (  a: in std_logic;
            y: out std_logic
    );
end not_gate;

architecture behavior of not_gate is
begin
    y <= not a;
end behavior;

-- Estructura del comparador de 1 bit
architecture estructura of comparador_1bit is
    signal x_neg, y_neg, x_igual_y, x_mayor_y: std_logic;
begin
    -- Instanciación de puertas
    u1: entity work.not_gate port map (y, y_neg);
    u2: entity work.and_gate port map (x, y_neg, x_mayor_y);
    u3: entity work.xnor_gate port map (x, y, x_igual_y);
    u4: entity work.and_gate port map (x_igual_y, gin, g_temp);
    u5: entity work.or_gate port map (x_mayor_y, g_temp, gout);
    u6: entity work.and_gate port map (x_igual_y, ein, eout);
end estructura;

-- c)
library IEEE;
use IEEE.Std_logic_1164.all;
use IEEE.Numeric_Std.all;
architecture estructura of comparador_Nbits is
    signal g_temp, e_temp: std_logic_vector (N-1 downto 0);
    signal gin_temp, ein_temp: std_logic_vector (N downto 0);
begin
    gin_temp(0) <= gin;
    ein_temp(0) <= ein;
    
    gen_comparadores: for i in 0 to N-1 generate
        comp: entity work.comparador_1bit
            port map (
                gout => g_temp(i),
                eout => e_temp(i),
                gin => gin_temp(i),
                ein => ein_temp(i),
                x => x(i),
                y => y(i)
            );
        gin_temp(i+1) <= g_temp(i);
        ein_temp(i+1) <= e_temp(i);
    end generate;
    
    gout <= gin_temp(N);
    eout <= ein_temp(N);
end estructura;

-- d)

library IEEE;
use IEEE.STD_LOGIC_1164.ALL;
use IEEE.NUMERIC_STD.ALL;

entity tb_comparador_Nbits is
end tb_comparador_Nbits;

architecture test of tb_comparador_Nbits is
    constant N : integer := 4;
    signal x, y: std_logic_vector (N-1 downto 0);
    signal gout, eout: std_logic;
    signal gin, ein: std_logic;
    
    component comparador_Nbits is
        generic ( N: integer := 4);
        port(   gout: out std_logic;
                eout: out std_logic;
                gin: in std_logic;
                ein: in std_logic;
                x: in std_logic_vector (N-1 downto 0);
                y: in std_logic_vector (N-1 downto 0)
        );
    end component;
begin
    uut: comparador_Nbits
        generic map (N => N)
        port map (
            gout => gout,
            eout => eout,
            gin => gin,
            ein => ein,
            x => x,
            y => y
        );
    
    -- Proceso de estimulación
    process
        variable error_count : integer := 0;
    begin
        gin <= '0';
        ein <= '1';
        
        -- Probar todas las combinaciones posibles para N=4
        for i in 0 to 2**N-1 loop
            for j in 0 to 2**N-1 loop
                x <= std_logic_vector(to_unsigned(i, N));
                y <= std_logic_vector(to_unsigned(j, N));
                wait for 10 ns;
                
                -- Verificar resultados
                if (i > j and gout /= '1') or (i <= j and gout = '1') then
                    error_count := error_count + 1;
                end if;
                
                if (i = j and eout /= '1') or (i /= j and eout = '1') then
                    error_count := error_count + 1;
                end if;
            end loop;
        end loop;
        
        -- Probar con gin=1, ein=0
        gin <= '1';
        ein <= '0';
        x <= "1111";
        y <= "1111";
        wait for 10 ns;
        if gout /= '1' or eout /= '0' then
            error_count := error_count + 1;
        end if;
        
        report "Simulación finalizada. Errores: " & integer'image(error_count);
        wait;
    end process;
end test;

IC_III/Parte_2/waveform2.vcd
$date
  Sun Apr 06 17:03:58 2025
$end
$version
  GHDL v0
$end
$timescale
  1 fs
$end
$scope module standard $end
$upscope $end
$scope module std_logic_1164 $end
$upscope $end
$scope module numeric_std $end
$upscope $end
$scope module tb_comparador_nbits $end
$var reg 4 ! x[3:0] $end
$var reg 4 " y[3:0] $end
$var reg 1 # gout $end
$var reg 1 $ eout $end
$var reg 1 % gin $end
$var reg 1 & ein $end
$scope module uut $end
$var reg 1 ' gout $end
$var reg 1 ( eout $end
$var reg 1 ) gin $end
$var reg 1 * ein $end
$var reg 4 + x[3:0] $end
$var reg 4 , y[3:0] $end
$var reg 4 - g_temp[3:0] $end
$var reg 4 . e_temp[3:0] $end
$var reg 5 / gin_temp[4:0] $end
$var reg 5 0 ein_temp[4:0] $end
$scope module gen_comparadores(0) $end
$scope module comp $end
$var reg 1 1 gout $end
$var reg 1 2 eout $end
$var reg 1 3 gin $end
$var reg 1 4 ein $end
$var reg 1 5 x $end
$var reg 1 6 y $end
$var reg 1 7 y_neg $end
$var reg 1 8 x_mayor_y $end
$var reg 1 9 x_igual_y $end
$var reg 1 : g_temp $end
$scope module u1 $end
$var reg 1 ; a $end
$var reg 1 < y $end
$upscope $end
$scope module u2 $end
$var reg 1 = a $end
$var reg 1 > b $end
$var reg 1 ? y $end
$upscope $end
$scope module u3 $end
$var reg 1 @ a $end
$var reg 1 A b $end
$var reg 1 B y $end
$upscope $end
$scope module u4 $end
$var reg 1 C a $end
$var reg 1 D b $end
$var reg 1 E y $end
$upscope $end
$scope module u5 $end
$var reg 1 F a $end
$var reg 1 G b $end
$var reg 1 H y $end
$upscope $end
$scope module u6 $end
$var reg 1 I a $end
$var reg 1 J b $end
$var reg 1 K y $end
$upscope $end
$upscope $end
$upscope $end
$scope module gen_comparadores(1) $end
$scope module comp $end
$var reg 1 L gout $end
$var reg 1 M eout $end
$var reg 1 N gin $end
$var reg 1 O ein $end
$var reg 1 P x $end
$var reg 1 Q y $end
$var reg 1 R y_neg $end
$var reg 1 S x_mayor_y $end
$var reg 1 T x_igual_y $end
$var reg 1 U g_temp $end
$scope module u1 $end
$var reg 1 V a $end
$var reg 1 W y $end
$upscope $end
$scope module u2 $end
$var reg 1 X a $end
$var reg 1 Y b $end
$var reg 1 Z y $end
$upscope $end
$scope module u3 $end
$var reg 1 [ a $end
$var reg 1 \ b $end
$var reg 1 ] y $end
$upscope $end
$scope module u4 $end
$var reg 1 ^ a $end
$var reg 1 _ b $end
$var reg 1 ` y $end
$upscope $end
$scope module u5 $end
$var reg 1 a a $end
$var reg 1 b b $end
$var reg 1 c y $end
$upscope $end
$scope module u6 $end
$var reg 1 d a $end
$var reg 1 e b $end
$var reg 1 f y $end
$upscope $end
$upscope $end
$upscope $end
$scope module gen_comparadores(2) $end
$scope module comp $end
$var reg 1 g gout $end
$var reg 1 h eout $end
$var reg 1 i gin $end
$var reg 1 j ein $end
$var reg 1 k x $end
$var reg 1 l y $end
$var reg 1 m y_neg $end
$var reg 1 n x_mayor_y $end
$var reg 1 o x_igual_y $end
$var reg 1 p g_temp $end
$scope module u1 $end
$var reg 1 q a $end
$var reg 1 r y $end
$upscope $end
$scope module u2 $end
$var reg 1 s a $end
$var reg 1 t b $end
$var reg 1 u y $end
$upscope $end
$scope module u3 $end
$var reg 1 v a $end
$var reg 1 w b $end
$var reg 1 x y $end
$upscope $end
$scope module u4 $end
$var reg 1 y a $end
$var reg 1 z b $end
$var reg 1 { y $end
$upscope $end
$scope module u5 $end
$var reg 1 | a $end
$var reg 1 } b $end
$var reg 1 !" y $end
$upscope $end
$scope module u6 $end
$var reg 1 "" a $end
$var reg 1 #" b $end
$var reg 1 $" y $end
$upscope $end
$upscope $end
$upscope $end
$scope module gen_comparadores(3) $end
$scope module comp $end
$var reg 1 %" gout $end
$var reg 1 &" eout $end
$var reg 1 '" gin $end
$var reg 1 (" ein $end
$var reg 1 )" x $end
$var reg 1 *" y $end
$var reg 1 +" y_neg $end
$var reg 1 ," x_mayor_y $end
$var reg 1 -" x_igual_y $end
$var reg 1 ." g_temp $end
$scope module u1 $end
$var reg 1 /" a $end
$var reg 1 0" y $end
$upscope $end
$scope module u2 $end
$var reg 1 1" a $end
$var reg 1 2" b $end
$var reg 1 3" y $end
$upscope $end
$scope module u3 $end
$var reg 1 4" a $end
$var reg 1 5" b $end
$var reg 1 6" y $end
$upscope $end
$scope module u4 $end
$var reg 1 7" a $end
$var reg 1 8" b $end
$var reg 1 9" y $end
$upscope $end
$scope module u5 $end
$var reg 1 :" a $end
$var reg 1 ;" b $end
$var reg 1 <" y $end
$upscope $end
$scope module u6 $end
$var reg 1 =" a $end
$var reg 1 >" b $end
$var reg 1 ?" y $end
$upscope $end
$upscope $end
$upscope $end
$upscope $end
$upscope $end
$enddefinitions $end
#0
b0000 !
b0000 "
0#
1$
0%
1&
0'
1(
0)
1*
b0000 +
b0000 ,
b0000 -
b1111 .
b00000 /
b11111 0
01
12
03
14
05
06
17
08
19
0:
0;
1<
0=
1>
0?
0@
0A
1B
1C
1D
1E
1F
0G
0H
0I
0J
0K
0L
1M
0N
1O
0P
0Q
1R
0S
1T
0U
0V
1W
0X
1Y
0Z
0[
0\
1]
1^
1_
1`
1a
0b
0c
0d
0e
0f
0g
1h
0i
1j
0k
0l
1m
0n
1o
0p
0q
1r
0s
1t
0u
0v
0w
1x
1y
1z
1{
1|
0}
0!"
0""
0#"
0$"
0%"
1&"
0'"
1("
0)"
0*"
1+"
0,"
1-"
0."
0/"
10"
01"
12"
03"
04"
05"
16"
17"
18"
19"
1:"
0;"
0<"
0="
0>"
0?"
#10000000
b0001 "
0$
0(
b0001 ,
b0000 .
b00001 0
02
16
07
09
1;
0<
0>
1A
0B
0C
0E
0F
0M
0O
0_
0`
0h
0j
0z
0{
0&"
0("
08"
09"
#20000000
b0010 "
b0010 ,
b0001 .
b00011 0
12
06
17
19
0;
1<
1>
0A
1B
1C
1E
1F
1O
1Q
0R
0T
1V
0W
0Y
1\
0]
0^
1_
0a
#30000000
b0011 "
b0011 ,
b0000 .
b00001 0
02
16
07
09
1;
0<
0>
1A
0B
0C
0E
0F
0O
0_
#40000000
b0100 "
b0100 ,
b0011 .
b00111 0
12
06
17
19
0;
1<
1>
0A
1B
1C
1E
1F
1M
1O
0Q
1R
1T
0V
1W
1Y
0\
1]
1^
1_
1`
1a
1j
1l
0m
0o
1q
0r
0t
1w
0x
0y
1z
0|
#50000000
b0101 "
b0101 ,
b0000 .
b00001 0
02
16
07
09
1;
0<
0>
1A
0B
0C
0E
0F
0M
0O
0_
0`
0j
0z
#60000000
b0110 "
b0110 ,
b0001 .
b00011 0
12
06
17
19
0;
1<
1>
0A
1B
1C
1E
1F
1O
1Q
0R
0T
1V
0W
0Y
1\
0]
0^
1_
0a
#70000000
b0111 "
b0111 ,
b0000 .
b00001 0
02
16
07
09
1;
0<
0>
1A
0B
0C
0E
0F
0O
0_
#80000000
b1000 "
b1000 ,
b0111 .
b01111 0
12
06
17
19
0;
1<
1>
0A
1B
1C
1E
1F
1M
1O
0Q
1R
1T
0V
1W
1Y
0\
1]
1^
1_
1`
1a
1h
1j
0l
1m
1o
0q
1r
1t
0w
1x
1y
1z
1{
1|
1("
1*"
0+"
0-"
1/"
00"
02"
15"
06"
07"
18"
0:"
#90000000
b1001 "
b1001 ,
b0000 .
b00001 0
02
16
07
09
1;
0<
0>
1A
0B
0C
0E
0F
0M
0O
0_
0`
0h
0j
0z
0{
0("
08"
#100000000
b1010 "
b1010 ,
b0001 .
b00011 0
12
06
17
19
0;
1<
1>
0A
1B
1C
1E
1F
1O
1Q
0R
0T
1V
0W
0Y
1\
0]
0^
1_
0a
#110000000
b1011 "
b1011 ,
b0000 .
b00001 0
02
16
07
09
1;
0<
0>
1A
0B
0C
0E
0F
0O
0_
#120000000
b1100 "
b1100 ,
b0011 .
b00111 0
12
06
17
19
0;
1<
1>
0A
1B
1C
1E
1F
1M
1O
0Q
1R
1T
0V
1W
1Y
0\
1]
1^
1_
1`
1a
1j
1l
0m
0o
1q
0r
0t
1w
0x
0y
1z
0|
#130000000
b1101 "
b1101 ,
b0000 .
b00001 0
02
16
07
09
1;
0<
0>
1A
0B
0C
0E
0F
0M
0O
0_
0`
0j
0z
#140000000
b1110 "
b1110 ,
b0001 .
b00011 0
12
06
17
19
0;
1<
1>
0A
1B
1C
1E
1F
1O
1Q
0R
0T
1V
0W
0Y
1\
0]
0^
1_
0a
#150000000
b1111 "
b1111 ,
b0000 .
b00001 0
02
16
07
09
1;
0<
0>
1A
0B
0C
0E
0F
0O
0_
#160000000
b0001 !
b0000 "
1#
1'
b0001 +
b0000 ,
b1111 -
b11110 /
11
15
06
17
18
0;
1<
1=
1>
1?
1@
0A
1I
1K
1L
1N
0Q
1R
1T
1U
0V
1W
1Y
0\
1]
1^
1a
1b
1c
1e
1f
1g
1i
0l
1m
1o
1p
0q
1r
1t
0w
1x
1y
1|
1}
1!"
1#"
1$"
1%"
1'"
0*"
1+"
1-"
1."
0/"
10"
12"
05"
16"
17"
1:"
1;"
1<"
1>"
1?"
#170000000
b0001 "
0#
1$
0'
1(
b0001 ,
b0000 -
b1111 .
b00000 /
b11111 0
01
12
16
07
08
19
1;
0<
0>
0?
1A
1B
1C
1E
1F
0I
0K
0L
1M
0N
1O
0U
1_
1`
0b
0c
0e
0f
0g
1h
0i
1j
0p
1z
1{
0}
0!"
0#"
0$"
0%"
1&"
0'"
1("
0."
18"
19"
0;"
0<"
0>"
0?"
#180000000
b0010 "
0$
0(
b0010 ,
b0001 -
b0000 .
b00010 /
b00001 0
11
02
06
17
18
09
0;
1<
1>
1?
0A
0B
0C
0E
0F
1I
1K
0M
1N
0O
1Q
0R
0T
1V
0W
0Y
1\
0]
0^
0_
0`
0a
1b
0h
0j
0z
0{
0&"
0("
08"
09"
#190000000
b0011 "
b0011 ,
b0000 -
b0001 .
b00000 /
b00011 0
01
12
16
07
08
19
1;
0<
0>
0?
1A
1B
1C
1E
1F
0I
0K
0N
1O
1_
0b
#200000000
b0100 "
b0100 ,
b0011 -
b0000 .
b00110 /
b00001 0
11
02
06
17
18
09
0;
1<
1>
1?
0A
0B
0C
0E
0F
1I
1K
1L
0M
1N
0O
0Q
1R
1T
1U
0V
1W
1Y
0\
1]
1^
0_
0`
1a
1b
1c
1e
1f
1i
0j
1l
0m
0o
1q
0r
0t
1w
0x
0y
0z
0|
1}
#210000000
b0101 "
b0101 ,
b0000 -
b0011 .
b00000 /
b00111 0
01
12
16
07
08
19
1;
0<
0>
0?
1A
1B
1C
1E
1F
0I
0K
0L
1M
0N
1O
0U
1_
1`
0b
0c
0e
0f
0i
1j
1z
0}
#220000000
b0110 "
b0110 ,
b0001 -
b0000 .
b00010 /
b00001 0
11
02
06
17
18
09
0;
1<
1>
1?
0A
0B
0C
0E
0F
1I
1K
0M
1N
0O
1Q
0R
0T
1V
0W
0Y
1\
0]
0^
0_
0`
0a
1b
0j
0z
#230000000
b0111 "
b0111 ,
b0000 -
b0001 .
b00000 /
b00011 0
01
12
16
07
08
19
1;
0<
0>
0?
1A
1B
1C
1E
1F
0I
0K
0N
1O
1_
0b
#240000000
b1000 "
b1000 ,
b0111 -
b0000 .
b01110 /
b00001 0
11
02
06
17
18
09
0;
1<
1>
1?
0A
0B
0C
0E
0F
1I
1K
1L
0M
1N
0O
0Q
1R
1T
1U
0V
1W
1Y
0\
1]
1^
0_
0`
1a
1b
1c
1e
1f
1g
0h
1i
0j
0l
1m
1o
1p
0q
1r
1t
0w
1x
1y
0z
0{
1|
1}
1!"
1#"
1$"
1'"
0("
1*"
0+"
0-"
1/"
00"
02"
15"
06"
07"
08"
0:"
1;"
#250000000
b1001 "
b1001 ,
b0000 -
b0111 .
b00000 /
b01111 0
01
12
16
07
08
19
1;
0<
0>
0?
1A
1B
1C
1E
1F
0I
0K
0L
1M
0N
1O
0U
1_
1`
0b
0c
0e
0f
0g
1h
0i
1j
0p
1z
1{
0}
0!"
0#"
0$"
0'"
1("
18"
0;"
#260000000
b1010 "
b1010 ,
b0001 -
b0000 .
b00010 /
b00001 0
11
02
06
17
18
09
0;
1<
1>
1?
0A
0B
0C
0E
0F
1I
1K
0M
1N
0O
1Q
0R
0T
1V
0W
0Y
1\
0]
0^
0_
0`
0a
1b
0h
0j
0z
0{
0("
08"
#270000000
b1011 "
b1011 ,
b0000 -
b0001 .
b00000 /
b00011 0
01
12
16
07
08
19
1;
0<
0>
0?
1A
1B
1C
1E
1F
0I
0K
0N
1O
1_
0b
#280000000
b1100 "
b1100 ,
b0011 -
b0000 .
b00110 /
b00001 0
11
02
06
17
18
09
0;
1<
1>
1?
0A
0B
0C
0E
0F
1I
1K
1L
0M
1N
0O
0Q
1R
1T
1U
0V
1W
1Y
0\
1]
1^
0_
0`
1a
1b
1c
1e
1f
1i
0j
1l
0m
0o
1q
0r
0t
1w
0x
0y
0z
0|
1}
#290000000
b1101 "
b1101 ,
b0000 -
b0011 .
b00000 /
b00111 0
01
12
16
07
08
19
1;
0<
0>
0?
1A
1B
1C
1E
1F
0I
0K
0L
1M
0N
1O
0U
1_
1`
0b
0c
0e
0f
0i
1j
1z
0}
#300000000
b1110 "
b1110 ,
b0001 -
b0000 .
b00010 /
b00001 0
11
02
06
17
18
09
0;
1<
1>
1?
0A
0B
0C
0E
0F
1I
1K
0M
1N
0O
1Q
0R
0T
1V
0W
0Y
1\
0]
0^
0_
0`
0a
1b
0j
0z
#310000000
b1111 "
b1111 ,
b0000 -
b0001 .
b00000 /
b00011 0
01
12
16
07
08
19
1;
0<
0>
0?
1A
1B
1C
1E
1F
0I
0K
0N
1O
1_
0b
#320000000
b0010 !
b0000 "
1#
1'
b0010 +
b0000 ,
b1110 -
b11100 /
05
06
17
0;
1<
0=
1>
0@
0A
1L
1P
0Q
1R
1S
0V
1W
1X
1Y
1Z
1[
0\
1d
1f
1g
1i
0l
1m
1o
1p
0q
1r
1t
0w
1x
1y
1|
1}
1!"
1#"
1$"
1%"
1'"
0*"
1+"
1-"
1."
0/"
10"
12"
05"
16"
17"
1:"
1;"
1<"
1>"
1?"
#330000000
b0001 "
b0001 ,
b0000 .
b00001 0
02
16
07
09
1;
0<
0>
1A
0B
0C
0E
0F
0O
0_
#340000000
b0010 "
0#
1$
0'
1(
b0010 ,
b0000 -
b1111 .
b00000 /
b11111 0
12
06
17
19
0;
1<
1>
0A
1B
1C
1E
1F
0L
1M
1O
1Q
0R
0S
1T
1V
0W
0Y
0Z
1\
1]
1^
1_
1`
1a
0d
0f
0g
1h
0i
1j
0p
1z
1{
0}
0!"
0#"
0$"
0%"
1&"
0'"
1("
0."
18"
19"
0;"
0<"
0>"
0?"
#350000000
b0011 "
0$
0(
b0011 ,
b0000 .
b00001 0
02
16
07
09
1;
0<
0>
1A
0B
0C
0E
0F
0M
0O
0_
0`
0h
0j
0z
0{
0&"
0("
08"
09"
#360000000
b0100 "
b0100 ,
b0010 -
b0001 .
b00100 /
b00011 0
12
06
17
19
0;
1<
1>
0A
1B
1C
1E
1F
1L
1O
0Q
1R
1S
0T
0V
1W
1Y
1Z
0\
0]
0^
1_
0a
1d
1f
1i
1l
0m
0o
1q
0r
0t
1w
0x
0y
0|
1}
#370000000
b0101 "
b0101 ,
b0000 .
b00001 0
02
16
07
09
1;
0<
0>
1A
0B
0C
0E
0F
0O
0_
#380000000
b0110 "
b0110 ,
b0000 -
b0011 .
b00000 /
b00111 0
12
06
17
19
0;
1<
1>
0A
1B
1C
1E
1F
0L
1M
1O
1Q
0R
0S
1T
1V
0W
0Y
0Z
1\
1]
1^
1_
1`
1a
0d
0f
0i
1j
1z
0}
#390000000
b0111 "
b0111 ,
b0000 .
b00001 0
02
16
07
09
1;
0<
0>
1A
0B
0C
0E
0F
0M
0O
0_
0`
0j
0z
#400000000
b1000 "
b1000 ,
b0110 -
b0001 .
b01100 /
b00011 0
12
06
17
19
0;
1<
1>
0A
1B
1C
1E
1F
1L
1O
0Q
1R
1S
0T
0V
1W
1Y
1Z
0\
0]
0^
1_
0a
1d
1f
1g
1i
0l
1m
1o
1p
0q
1r
1t
0w
1x
1y
1|
1}
1!"
1#"
1$"
1'"
1*"
0+"
0-"
1/"
00"
02"
15"
06"
07"
0:"
1;"
#410000000
b1001 "
b1001 ,
b0000 .
b00001 0
02
16
07
09
1;
0<
0>
1A
0B
0C
0E
0F
0O
0_
#420000000
b1010 "
b1010 ,
b0000 -
b0111 .
b00000 /
b01111 0
12
06
17
19
0;
1<
1>
0A
1B
1C
1E
1F
0L
1M
1O
1Q
0R
0S
1T
1V
0W
0Y
0Z
1\
1]
1^
1_
1`
1a
0d
0f
0g
1h
0i
1j
0p
1z
1{
0}
0!"
0#"
0$"
0'"
1("
18"
0;"
#430000000
b1011 "
b1011 ,
b0000 .
b00001 0
02
16
07
09
1;
0<
0>
1A
0B
0C
0E
0F
0M
0O
0_
0`
0h
0j
0z
0{
0("
08"
#440000000
b1100 "
b1100 ,
b0010 -
b0001 .
b00100 /
b00011 0
12
06
17
19
0;
1<
1>
0A
1B
1C
1E
1F
1L
1O
0Q
1R
1S
0T
0V
1W
1Y
1Z
0\
0]
0^
1_
0a
1d
1f
1i
1l
0m
0o
1q
0r
0t
1w
0x
0y
0|
1}
#450000000
b1101 "
b1101 ,
b0000 .
b00001 0
02
16
07
09
1;
0<
0>
1A
0B
0C
0E
0F
0O
0_
#460000000
b1110 "
b1110 ,
b0000 -
b0011 .
b00000 /
b00111 0
12
06
17
19
0;
1<
1>
0A
1B
1C
1E
1F
0L
1M
1O
1Q
0R
0S
1T
1V
0W
0Y
0Z
1\
1]
1^
1_
1`
1a
0d
0f
0i
1j
1z
0}
#470000000
b1111 "
b1111 ,
b0000 .
b00001 0
02
16
07
09
1;
0<
0>
1A
0B
0C
0E
0F
0M
0O
0_
0`
0j
0z
#480000000
b0011 !
b0000 "
1#
1'
b0011 +
b0000 ,
b1111 -
b11110 /
11
15
06
17
18
0;
1<
1=
1>
1?
1@
0A
1I
1K
1L
1N
0Q
1R
1S
0T
0V
1W
1Y
1Z
0\
0]
0^
0a
1b
1d
1f
1g
1i
0l
1m
1o
1p
0q
1r
1t
0w
1x
1y
1|
1}
1!"
1#"
1$"
1%"
1'"
0*"
1+"
1-"
1."
0/"
10"
12"
05"
16"
17"
1:"
1;"
1<"
1>"
1?"
#490000000
b0001 "
b0001 ,
b1110 -
b0001 .
b11100 /
b00011 0
01
12
16
07
08
19
1;
0<
0>
0?
1A
1B
1C
1E
1F
0I
0K
0N
1O
1_
0b
#500000000
b0010 "
1#
0$
1'
0(
b0010 ,
b1111 -
b0000 .
b11110 /
b00001 0
11
02
06
17
18
09
0;
1<
1>
1?
0A
0B
0C
0E
0F
1I
1K
1L
0M
1N
0O
1Q
0R
0S
1T
1U
1V
0W
0Y
0Z
1\
1]
1^
0_
0`
1a
1b
1c
0d
1e
1f
1g
0h
1i
0j
1p
0z
0{
1}
1!"
1#"
1$"
1%"
0&"
1'"
0("
1."
08"
09"
1;"
1<"
1>"
1?"
#510000000
b0011 "
0#
1$
0'
1(
b0011 ,
b0000 -
b1111 .
b00000 /
b11111 0
01
12
16
07
08
19
1;
0<
0>
0?
1A
1B
1C
1E
1F
0I
0K
0L
1M
0N
1O
0U
1_
1`
0b
0c
0e
0f
0g
1h
0i
1j
0p
1z
1{
0}
0!"
0#"
0$"
0%"
1&"
0'"
1("
0."
18"
19"
0;"
0<"
0>"
0?"
#520000000
b0100 "
0$
0(
b0100 ,
b0011 -
b0000 .
b00110 /
b00001 0
11
02
06
17
18
09
0;
1<
1>
1?
0A
0B
0C
0E
0F
1I
1K
1L
0M
1N
0O
0Q
1R
1S
0T
0V
1W
1Y
1Z
0\
0]
0^
0_
0`
0a
1b
1d
1f
0h
1i
0j
1l
0m
0o
1q
0r
0t
1w
0x
0y
0z
0{
0|
1}
0&"
0("
08"
09"
#530000000
b0101 "
b0101 ,
b0010 -
b0001 .
b00100 /
b00011 0
01
12
16
07
08
19
1;
0<
0>
0?
1A
1B
1C
1E
1F
0I
0K
0N
1O
1_
0b
#540000000
b0110 "
b0110 ,
b0011 -
b0000 .
b00110 /
b00001 0
11
02
06
17
18
09
0;
1<
1>
1?
0A
0B
0C
0E
0F
1I
1K
1L
0M
1N
0O
1Q
0R
0S
1T
1U
1V
0W
0Y
0Z
1\
1]
1^
0_
0`
1a
1b
1c
0d
1e
1f
1i
0j
0z
1}
#550000000
b0111 "
b0111 ,
b0000 -
b0011 .
b00000 /
b00111 0
01
12
16
07
08
19
1;
0<
0>
0?
1A
1B
1C
1E
1F
0I
0K
0L
1M
0N
1O
0U
1_
1`
0b
0c
0e
0f
0i
1j
1z
0}
#560000000
b1000 "
b1000 ,
b0111 -
b0000 .
b01110 /
b00001 0
11
02
06
17
18
09
0;
1<
1>
1?
0A
0B
0C
0E
0F
1I
1K
1L
0M
1N
0O
0Q
1R
1S
0T
0V
1W
1Y
1Z
0\
0]
0^
0_
0`
0a
1b
1d
1f
1g
0h
1i
0j
0l
1m
1o
1p
0q
1r
1t
0w
1x
1y
0z
0{
1|
1}
1!"
1#"
1$"
1'"
0("
1*"
0+"
0-"
1/"
00"
02"
15"
06"
07"
08"
0:"
1;"
#570000000
b1001 "
b1001 ,
b0110 -
b0001 .
b01100 /
b00011 0
01
12
16
07
08
19
1;
0<
0>
0?
1A
1B
1C
1E
1F
0I
0K
0N
1O
1_
0b
#580000000
b1010 "
b1010 ,
b0111 -
b0000 .
b01110 /
b00001 0
11
02
06
17
18
09
0;
1<
1>
1?
0A
0B
0C
0E
0F
1I
1K
1L
0M
1N
0O
1Q
0R
0S
1T
1U
1V
0W
0Y
0Z
1\
1]
1^
0_
0`
1a
1b
1c
0d
1e
1f
1g
0h
1i
0j
1p
0z
0{
1}
1!"
1#"
1$"
1'"
0("
08"
1;"
#590000000
b1011 "
b1011 ,
b0000 -
b0111 .
b00000 /
b01111 0
01
12
16
07
08
19
1;
0<
0>
0?
1A
1B
1C
1E
1F
0I
0K
0L
1M
0N
1O
0U
1_
1`
0b
0c
0e
0f
0g
1h
0i
1j
0p
1z
1{
0}
0!"
0#"
0$"
0'"
1("
18"
0;"
#600000000
b1100 "
b1100 ,
b0011 -
b0000 .
b00110 /
b00001 0
11
02
06
17
18
09
0;
1<
1>
1?
0A
0B
0C
0E
0F
1I
1K
1L
0M
1N
0O
0Q
1R
1S
0T
0V
1W
1Y
1Z
0\
0]
0^
0_
0`
0a
1b
1d
1f
0h
1i
0j
1l
0m
0o
1q
0r
0t
1w
0x
0y
0z
0{
0|
1}
0("
08"
#610000000
b1101 "
b1101 ,
b0010 -
b0001 .
b00100 /
b00011 0
01
12
16
07
08
19
1;
0<
0>
0?
1A
1B
1C
1E
1F
0I
0K
0N
1O
1_
0b
#620000000
b1110 "
b1110 ,
b0011 -
b0000 .
b00110 /
b00001 0
11
02
06
17
18
09
0;
1<
1>
1?
0A
0B
0C
0E
0F
1I
1K
1L
0M
1N
0O
1Q
0R
0S
1T
1U
1V
0W
0Y
0Z
1\
1]
1^
0_
0`
1a
1b
1c
0d
1e
1f
1i
0j
0z
1}
#630000000
b1111 "
b1111 ,
b0000 -
b0011 .
b00000 /
b00111 0
01
12
16
07
08
19
1;
0<
0>
0?
1A
1B
1C
1E
1F
0I
0K
0L
1M
0N
1O
0U
1_
1`
0b
0c
0e
0f
0i
1j
1z
0}
#640000000
b0100 !
b0000 "
1#
1'
b0100 +
b0000 ,
b1100 -
b11000 /
05
06
17
0;
1<
0=
1>
0@
0A
0P
0Q
1R
0V
1W
0X
1Y
0[
0\
1g
1k
0l
1m
1n
0q
1r
1s
1t
1u
1v
0w
1""
1$"
1%"
1'"
0*"
1+"
1-"
1."
0/"
10"
12"
05"
16"
17"
1:"
1;"
1<"
1>"
1?"
#650000000
b0001 "
b0001 ,
b0000 .
b00001 0
02
16
07
09
1;
0<
0>
1A
0B
0C
0E
0F
0M
0O
0_
0`
0j
0z
#660000000
b0010 "
b0010 ,
b0001 .
b00011 0
12
06
17
19
0;
1<
1>
0A
1B
1C
1E
1F
1O
1Q
0R
0T
1V
0W
0Y
1\
0]
0^
1_
0a
#670000000
b0011 "
b0011 ,
b0000 .
b00001 0
02
16
07
09
1;
0<
0>
1A
0B
0C
0E
0F
0O
0_
#680000000
b0100 "
0#
1$
0'
1(
b0100 ,
b0000 -
b1111 .
b00000 /
b11111 0
12
06
17
19
0;
1<
1>
0A
1B
1C
1E
1F
1M
1O
0Q
1R
1T
0V
1W
1Y
0\
1]
1^
1_
1`
1a
0g
1h
1j
1l
0m
0n
1o
1q
0r
0t
0u
1w
1x
1y
1z
1{
1|
0""
0$"
0%"
1&"
0'"
1("
0."
18"
19"
0;"
0<"
0>"
0?"
#690000000
b0101 "
0$
0(
b0101 ,
b0000 .
b00001 0
02
16
07
09
1;
0<
0>
1A
0B
0C
0E
0F
0M
0O
0_
0`
0h
0j
0z
0{
0&"
0("
08"
09"
#700000000
b0110 "
b0110 ,
b0001 .
b00011 0
12
06
17
19
0;
1<
1>
0A
1B
1C
1E
1F
1O
1Q
0R
0T
1V
0W
0Y
1\
0]
0^
1_
0a
